directsql/__init__.py
directsql/connector.py
directsql/pg_connector.py
directsql/query_util.py
directsql-0.7.1.dist-info/LICENSE
directsql-0.7.1.dist-info/METADATA
directsql-0.7.1.dist-info/WHEEL
directsql-0.7.1.dist-info/top_level.txt
directsql-0.7.1.dist-info/RECORD
