Metadata-Version: 2.1
Name: directsql
Version: 0.7.1
Summary: 一个简单的使用python操作mysql的工具，提供了一些类似sql语法的方法，最终拼接成sql。可以很好地处理一些常见场景，不依赖orm 的同时避免手写大量sql。
Home-page: https://github.com/lishukan/directsql
Author: surecanlee
Author-email: lishukan@qq.com
License: MIT License
Platform: UNKNOWN
Requires-Dist: DBUtils (>=1.13.0)
